etag/__init__.py
etag_middleware-0.2.0.dist-info/LICENSE
etag_middleware-0.2.0.dist-info/METADATA
etag_middleware-0.2.0.dist-info/WHEEL
etag_middleware-0.2.0.dist-info/top_level.txt
etag_middleware-0.2.0.dist-info/RECORD
